tts_mos_test_mturk/__init__.py
tts_mos_test_mturk/common.py
tts_mos_test_mturk/correlations.py
tts_mos_test_mturk/df_generation.py
tts_mos_test_mturk/evaluation_data.py
tts_mos_test_mturk/io.py
tts_mos_test_mturk/logging.py
tts_mos_test_mturk/result.py
tts_mos_test_mturk/typing.py
tts_mos_test_mturk/masking/__init__.py
tts_mos_test_mturk/masking/age_group_mask.py
tts_mos_test_mturk/masking/assignment_count_mask.py
tts_mos_test_mturk/masking/assignment_id_mask.py
tts_mos_test_mturk/masking/etc.py
tts_mos_test_mturk/masking/gender_mask.py
tts_mos_test_mturk/masking/listening_device_mask.py
tts_mos_test_mturk/masking/mask_factory.py
tts_mos_test_mturk/masking/masked_count_mask.py
tts_mos_test_mturk/masking/masks.py
tts_mos_test_mturk/masking/merge.py
tts_mos_test_mturk/masking/outlier_mask.py
tts_mos_test_mturk/masking/reverse.py
tts_mos_test_mturk/masking/state_mask.py
tts_mos_test_mturk/masking/time_mask.py
tts_mos_test_mturk/masking/worker_correlation_mask.py
tts_mos_test_mturk/masking/worker_id_mask.py
tts_mos_test_mturk/statistics/__init__.py
tts_mos_test_mturk/statistics/algorithm_sentence_stats.py
tts_mos_test_mturk/statistics/algorithm_worker_stats.py
tts_mos_test_mturk/statistics/update_stats.py
tts_mos_test_mturk/statistics/worker_assignment_stats.py
tts_mos_test_mturk_cli/__init__.py
tts_mos_test_mturk_cli/argparse_helper.py
tts_mos_test_mturk_cli/cli.py
tts_mos_test_mturk_cli/default_args.py
tts_mos_test_mturk_cli/globals.py
tts_mos_test_mturk_cli/helper.py
tts_mos_test_mturk_cli/logging_configuration.py
tts_mos_test_mturk_cli/types.py
tts_mos_test_mturk_cli/validation.py
tts_mos_test_mturk_cli/parsers/__init__.py
tts_mos_test_mturk_cli/parsers/init_parser.py
tts_mos_test_mturk_cli/parsers/masks_parsers.py
tts_mos_test_mturk_cli/parsers/mturk_parsers.py
tts_mos_test_mturk_cli/parsers/stats_parsers.py
tts_mos_test_mturk_tests/__init__.py
tts_mos_test_mturk_tests/common_py/__init__.py
tts_mos_test_mturk_tests/common_py/test_get_rating.py
tts_mos_test_mturk-0.0.2.dist-info/LICENSE
tts_mos_test_mturk-0.0.2.dist-info/METADATA
tts_mos_test_mturk-0.0.2.dist-info/WHEEL
tts_mos_test_mturk-0.0.2.dist-info/entry_points.txt
tts_mos_test_mturk-0.0.2.dist-info/top_level.txt
tts_mos_test_mturk-0.0.2.dist-info/RECORD
