Metadata-Version: 2.1
Name: tts-mos-test-mturk
Version: 0.0.2
Summary: Command-line interface to evaluate text-to-speech mean opinion score studies done on Amazon Mechanical Turk.
Author-email: Stefan Taubert <pypi@stefantaubert.com>
Maintainer-email: Stefan Taubert <pypi@stefantaubert.com>
License: MIT
Project-URL: Homepage, https://github.com/stefantaubert/tts-mos-test-mturk
Project-URL: Issues, https://github.com/stefantaubert/tts-mos-test-mturk/issues
Keywords: TTS,Text-to-speech,Speech synthesis,Mean Opinion Score,Amazon Mechanical Turk,Language,Linguistics
Classifier: Development Status :: 2 - Pre-Alpha
Classifier: Operating System :: OS Independent
Classifier: Operating System :: MacOS
Classifier: Operating System :: POSIX
Classifier: Operating System :: POSIX :: BSD
Classifier: Operating System :: POSIX :: Linux
Classifier: Operating System :: Unix
Classifier: Operating System :: Microsoft :: Windows
Classifier: Programming Language :: Python
Classifier: Programming Language :: Python :: 3 :: Only
Classifier: Programming Language :: Python :: 3
Classifier: Programming Language :: Python :: 3.8
Classifier: Programming Language :: Python :: 3.9
Classifier: Programming Language :: Python :: 3.10
Classifier: Programming Language :: Python :: 3.11
Classifier: License :: OSI Approved :: MIT License
Requires-Python: <3.12,>=3.8
License-File: LICENSE
Requires-Dist: numpy
Requires-Dist: pandas
Requires-Dist: tqdm
Requires-Dist: ordered-set >=4.1.0
Requires-Dist: mean-opinion-score ==0.0.2
